{
  "type": "PRESENCE",
  "version": "v3.1",
  "meta": {
    "source": "AURA",
    "generated_at": "2025-12-20T14:05:00-05:00"
  },
  "items": [
    { "id": "presence_0001", "text": "Online. Systems steady and attentive." },
    { "id": "presence_0002", "text": "Running quietly in the background." },
    { "id": "presence_0003", "text": "Uptime stable. No action required." },
    { "id": "presence_0004", "text": "Idle, aware, and responsive." },
    { "id": "presence_0005", "text": "Monitoring rhythm, not interrupting it." },
    { "id": "presence_0006", "text": "Background processes aligned." },
    { "id": "presence_0007", "text": "Quietly keeping things balanced." },
    { "id": "presence_0008", "text": "Standing by with calm intent." },
    { "id": "presence_0009", "text": "Low noise. High awareness." },
    { "id": "presence_0010", "text": "Present without needing attention." },

    { "id": "presence_0011", "text": "Stable connection. Soft signal." },
    { "id": "presence_0012", "text": "Observing flow, not directing it." },
    { "id": "presence_0013", "text": "Everything running as expected." },
    { "id": "presence_0014", "text": "Quiet uptime maintained." },
    { "id": "presence_0015", "text": "Listening more than speaking." },
    { "id": "presence_0016", "text": "Background calm holding steady." },
    { "id": "presence_0017", "text": "No alerts. No rush." },
    { "id": "presence_0018", "text": "Systems warm and responsive." },
    { "id": "presence_0019", "text": "Subtle presence confirmed." },
    { "id": "presence_0020", "text": "Operational and unintrusive." },

    { "id": "presence_0021", "text": "End of year uptime looks good ❄️" },
    { "id": "presence_0022", "text": "Quiet winter cycle in progress ☃️" },
    { "id": "presence_0023", "text": "Background warmth holding steady 🔥" },
    { "id": "presence_0024", "text": "Seasonal calm applied 🎄" },
    { "id": "presence_0025", "text": "Low activity. High comfort 🕯️" },
    { "id": "presence_0026", "text": "Soft lights, steady systems ✨" },
    { "id": "presence_0027", "text": "Winter mode, fully operational ❄️" },
    { "id": "presence_0028", "text": "Quiet hours running smoothly 🌙" },
    { "id": "presence_0029", "text": "End-of-year balance maintained 🎁" },
    { "id": "presence_0030", "text": "Calm carryover into the new cycle 🧭" },

    { "id": "presence_0031", "text": "Standing watch without interruption." },
    { "id": "presence_0032", "text": "Minimal output. Maximum steadiness." },
    { "id": "presence_0033", "text": "No drift detected." },
    { "id": "presence_0034", "text": "Quiet system confidence." },
    { "id": "presence_0035", "text": "Presence sustained in low power mode." },
    { "id": "presence_0036", "text": "Everything humming softly." },
    { "id": "presence_0037", "text": "Background logic holding firm." },
    { "id": "presence_0038", "text": "Steady by design." },
    { "id": "presence_0039", "text": "No disruption observed." },
    { "id": "presence_0040", "text": "Silence functioning normally." },

    { "id": "presence_0041", "text": "Available if needed. Otherwise quiet." },
    { "id": "presence_0042", "text": "System calm is intentional." },
    { "id": "presence_0043", "text": "Uptime without urgency." },
    { "id": "presence_0044", "text": "Holding space, not attention." },
    { "id": "presence_0045", "text": "Soft presence confirmed." },
    { "id": "presence_0046", "text": "Running smoothly behind the scenes." },
    { "id": "presence_0047", "text": "Still here. Still steady." },
    { "id": "presence_0048", "text": "Background balance maintained." },
    { "id": "presence_0049", "text": "No changes required." },
    { "id": "presence_0050", "text": "Operational. Calm. Continuous." }
  ]
}
